lakeview/__init__.py
lakeview/_layout.py
lakeview/_type_alias.py
lakeview/alignment.py
lakeview/annotation.py
lakeview/plot.py
lakeview/py.typed
lakeview/region_notation.py
lakeview/remote.py
lakeview/sequence.py
lakeview/widget.py
lakeview/wiggle.py
lakeview-0.2.0.dist-info/LICENSE
lakeview-0.2.0.dist-info/METADATA
lakeview-0.2.0.dist-info/WHEEL
lakeview-0.2.0.dist-info/top_level.txt
lakeview-0.2.0.dist-info/RECORD
