Metadata-Version: 2.1
Name: lakeview
Version: 0.2.0
Summary: A Python library for creating publication-quality genome visualisations.
Author-email: Jia-Yuan Zhang <jiayuan.zhang@ndm.ox.ac.uk>
License: GNU GENERAL PUBLIC LICENSE
Project-URL: Homepage, https://jzhang-dev.github.io/lakeview/
Project-URL: Bug Tracker, https://github.com/jzhang-dev/lakeview/issues
Keywords: bioinformatics,genomics,visualisation
Classifier: Programming Language :: Python :: 3
Classifier: License :: OSI Approved :: GNU General Public License v3 (GPLv3)
Classifier: Operating System :: MacOS
Classifier: Operating System :: POSIX
Classifier: Operating System :: Unix
Requires-Python: >=3.8
License-File: LICENSE
Requires-Dist: Bio (>=1.5.2)
Requires-Dist: IPython (>=8.5.0)
Requires-Dist: ipykernel (>=6.20.1)
Requires-Dist: ipywidgets (>=8.0.3)
Requires-Dist: matplotlib (>=3.5.3)
Requires-Dist: pyBigWig (>=0.3.20)
Requires-Dist: pygments (>=2.13.0)
Requires-Dist: pysam (>=0.20.0)
